pyfr24/__init__.py
pyfr24/cli.py
pyfr24/client.py
pyfr24/exceptions.py
pyfr24/logging.py
pyfr24-0.1.10.dist-info/licenses/LICENSE
tests/__init__.py
tests/analyze_gaps.py
tests/check_destinations.py
tests/compare_flights.py
tests/deep_api_test.py
tests/final_test.py
tests/investigate_structure.py
tests/run_tests.py
tests/test_client.py
tests/test_exceptions.py
tests/test_flight_lookup.py
tests/test_flight_summary.py
tests/test_logging.py
tests/test_pagination.py
tests/test_ua1584.py
pyfr24-0.1.10.dist-info/METADATA
pyfr24-0.1.10.dist-info/WHEEL
pyfr24-0.1.10.dist-info/entry_points.txt
pyfr24-0.1.10.dist-info/top_level.txt
pyfr24-0.1.10.dist-info/RECORD
